topbid/__init__.py
topbid/orderbook.py
topbid/scheduler.py
topbid-3.0.2.dist-info/LICENSE
topbid-3.0.2.dist-info/METADATA
topbid-3.0.2.dist-info/WHEEL
topbid-3.0.2.dist-info/top_level.txt
topbid-3.0.2.dist-info/RECORD
