Metadata-Version: 2.1
Name: topbid
Version: 3.0.2
Summary: Helper library to fetch current best bid/ask from crypto exchanges orderbook APIs
Home-page: https://github.com/tferreira/topbid
Author: Thomas Ferreira
Author-email: fulura@gmail.com
Classifier: Programming Language :: Python :: 3
Classifier: Operating System :: OS Independent
Requires-Python: >=3.8
Provides-Extra: dev
License-File: LICENSE
